abc/__init__.py
abc/print1.py
abc/print2.py
packagetest/__init__.py
packagetest/print1.py
packagetest/print2.py
pyaudioaoqingy/pyaudio.py
pyaudioaoqingy-1.0.dist-info/METADATA
pyaudioaoqingy-1.0.dist-info/WHEEL
pyaudioaoqingy-1.0.dist-info/top_level.txt
pyaudioaoqingy-1.0.dist-info/RECORD
