Metadata-Version: 2.1
Name: pyaudioaoqingy
Version: 1.0
Summary: A olddriver
Home-page: UNKNOWN
Author: Qingtai
Author-email: 1120359293@qq.com
License: UNKNOWN
Platform: UNKNOWN
